netlibapi/__init__.py
netlibapi-1.0.dist-info/LICENSE
netlibapi-1.0.dist-info/WHEEL
netlibapi-1.0.dist-info/METADATA
netlibapi-1.0.dist-info/RECORD
