Metadata-Version: 2.1
Name: netlibapi
Version: 1.0
Summary: netlibapi
Author-email: mohammad belal <m0x0user@gmail.com>
Classifier: License :: OSI Approved :: MIT License
Project-URL: Home, https://github.com/mohammadxdcoder/netlibapi
